calculator_mcp_service/__init__.py
calculator_mcp_service/calculator.py
calculator_mcp_service-0.1.0.dist-info/licenses/LICENSE
calculator_mcp_service-0.1.0.dist-info/METADATA
calculator_mcp_service-0.1.0.dist-info/WHEEL
calculator_mcp_service-0.1.0.dist-info/top_level.txt
calculator_mcp_service-0.1.0.dist-info/RECORD
