Metadata-Version: 2.4
Name: calculator_mcp_service
Version: 0.1.0
Summary: A simple calculator MCP service supporting basic arithmetic operations
Author-email: TangYongKang <316674908@qq.com>
License: MIT License
Classifier: Programming Language :: Python :: 3
Classifier: License :: OSI Approved :: MIT License
Classifier: Operating System :: OS Independent
Requires-Python: >=3.6
License-File: LICENSE
Dynamic: license-file
